audio_sed/sed_config.py
audio_sed/pytorch/audio_augmentations.py
audio_sed/pytorch/sed_block.py
audio_sed/pytorch/sed_models.py
audio_sed/tensorflow/sed_block.py
audio_sed/tensorflow/sed_models.py
audio_sed-0.0.2.1.dist-info/licenses/LICENSE
audio_sed-0.0.2.1.dist-info/METADATA
audio_sed-0.0.2.1.dist-info/WHEEL
audio_sed-0.0.2.1.dist-info/top_level.txt
audio_sed-0.0.2.1.dist-info/RECORD
