Metadata-Version: 2.4
Name: audio_sed
Version: 0.0.2.1
Summary: Implementation of audio SED architecture for tensorflow and pytorch.
Home-page: https://github.com/Shiro-LK/SoundEventDetection
Download-URL: https://github.com/Shiro-LK/SoundEventDetection.git
Author: Shiro-LK
Author-email: shirosaki94@gmail.com
License: MIT License
Keywords: torch,tensorflow,audio_sed
Classifier: Development Status :: 5 - Production/Stable
Classifier: Programming Language :: Python :: 3.7
Classifier: Programming Language :: Python :: 3.8
License-File: LICENSE
Requires-Dist: numpy
Requires-Dist: pytest
Requires-Dist: tensorflow
Requires-Dist: torch
Dynamic: author
Dynamic: author-email
Dynamic: classifier
Dynamic: description
Dynamic: description-content-type
Dynamic: download-url
Dynamic: home-page
Dynamic: keywords
Dynamic: license
Dynamic: license-file
Dynamic: requires-dist
Dynamic: summary
